poetry.lock
wordle_trainer/__init__.py
wordle_trainer/wordle.py
wordle_trainer/wordle_dictionary.py
wordle_trainer/wordle_test.py
wordle_trainer/words_dictionary.json
wordle_trainer-0.0.1.dist-info/entry_points.txt
wordle_trainer-0.0.1.dist-info/LICENSE.txt
wordle_trainer-0.0.1.dist-info/WHEEL
wordle_trainer-0.0.1.dist-info/METADATA
wordle_trainer-0.0.1.dist-info/RECORD
