Metadata-Version: 2.1
Name: wordle-trainer
Version: 0.0.1
Summary: A cli wordle clone that gives you hints as you play.
Home-page: https://github.com/maxb2/wordle-trainer
License: MIT
Author: Matthew Anderson
Author-email: matt@manderscience.com
Requires-Python: >=3.9.6,<4.0.0
Classifier: License :: OSI Approved :: MIT License
Classifier: Programming Language :: Python :: 3
Classifier: Programming Language :: Python :: 3.10
Requires-Dist: typer (>=0.4.0,<0.5.0)
Project-URL: Repository, https://github.com/maxb2/wordle-trainer
